<Element>

    <!--GENERAL-->
    <Item>
        <TextId>9000</TextId>
        <Text>Talna plošča</Text>
    </Item>

    <Item>
        <TextId>9001</TextId>
        <Text>Geometrija</Text>
    </Item>

    <!--PLATE-->
    <Item>
        <TextId>1000</TextId>
        <Text>Parametri plošče</Text>
    </Item>

    <Item>
        <TextId>1001</TextId>
        <Text>Širina</Text>
    </Item>

    <Item>
        <TextId>1002</TextId>
        <Text>Globina</Text>
    </Item>

    <Item>
        <TextId>1003</TextId>
        <Text>Debelina</Text>
    </Item>

    <Item>
        <TextId>1004</TextId>
        <Text>Standard</Text>
    </Item>

    <Item>
        <TextId>1005</TextId>
        <Text>Samodejno</Text>
    </Item>

    <Item>
        <TextId>1006</TextId>
        <Text>Razmak</Text>
    </Item>

    <Item>
        <TextId>1007</TextId>
        <Text>Velikost</Text>
    </Item>

    <Item>
        <TextId>1008</TextId>
        <Text>Pravokotnik</Text>
    </Item>

    <Item>
        <TextId>1009</TextId>
        <Text>Krog</Text>
    </Item>

    <Item>
        <TextId>1010</TextId>
        <Text>Oblika plošče</Text>
    </Item>

    <Item>
        <TextId>1011</TextId>
        <Text>Fi</Text>
    </Item>

    <!--BOLT-->
    <Item>
        <TextId>2000</TextId>
        <Text>Parametri sidra</Text>
    </Item>

    <Item>
        <TextId>2001</TextId>
        <Text>Robni odmik</Text>
    </Item>

    <Item>
        <TextId>2002</TextId>
        <Text>Število čepov</Text>
    </Item>

    <Item>
        <TextId>2003</TextId>
        <Text>Število čepov</Text>
    </Item>

    <Item>
        <TextId>2004</TextId>
        <Text>Tip kljuke</Text>
    </Item>

    <Item>
        <TextId>2005</TextId>
        <Text>Headed/L-kljuka/J-kljuka</Text>
    </Item>

    <Item>
        <TextId>2006</TextId>
        <Text>Velikost</Text>
    </Item>

    <Item>
        <TextId>2007</TextId>
        <Text>Dolžina</Text>
    </Item>

    <Item>
        <TextId>2008</TextId>
        <Text>Podložne ploščice</Text>
    </Item>

    <Item>
        <TextId>2009</TextId>
        <Text>Razred sidra</Text>
    </Item>

    <Item>
        <TextId>2010</TextId>
        <Text>Stopnja detajliranosti</Text>
    </Item>

    <Item>
        <TextId>2011</TextId>
        <Text>Nizko</Text>
    </Item>

    <Item>
        <TextId>2012</TextId>
        <Text>Srednje veliko</Text>
    </Item>

    <Item>
        <TextId>2013</TextId>
        <Text>Visoko</Text>
    </Item>

    <Item>
        <TextId>2014</TextId>
        <Text>Število čepov</Text>
    </Item>

    <!--WELD-->
    <Item>
        <TextId>3000</TextId>
        <Text>Parametri zvara</Text>
    </Item>

    <Item>
        <TextId>3001</TextId>
        <Text>Tip zvara</Text>
    </Item>

    <Item>
        <TextId>3002</TextId>
        <Text>Poličrta / zaokrožitev / konveksno / konkavno</Text>
    </Item>

    <Item>
        <TextId>3003</TextId>
        <Text>Širina zvara</Text>
    </Item>

    <Item>
        <TextId>3004</TextId>
        <Text>Kót zvara</Text>
    </Item>

    <Item>
        <TextId>3005</TextId>
        <Text>Dolžina zvara</Text>
    </Item>

    <Item>
        <TextId>3006</TextId>
        <Text>Globina zvara</Text>
    </Item>

    <Item>
        <TextId>3007</TextId>
        <Text>Zvar v polju</Text>
    </Item>

    <Item>
        <TextId>3008</TextId>
        <Text>Opomba</Text>
    </Item>

    <Item>
        <TextId>3009</TextId>
        <Text>Standard</Text>
    </Item>

    <Item>
        <TextId>3010</TextId>
        <Text>Krak/flanša</Text>
    </Item>

    <Item>
        <TextId>3011</TextId>
        <Text> </Text>
    </Item>

    <Item>
        <TextId>3012</TextId>
        <Text>Varjena flanša</Text>
    </Item>

    <Item>
        <TextId>3013</TextId>
        <Text>Krak zvara</Text>
    </Item>

    <!--STIFFENER-->
    <Item>
        <TextId>4000</TextId>
        <Text>Parametri togosti</Text>
    </Item>

    <Item>
        <TextId>4001</TextId>
        <Text>Horizontalna togost</Text>
    </Item>

    <Item>
        <TextId>4002</TextId>
        <Text>Center</Text>
    </Item>

    <Item>
        <TextId>4003</TextId>
        <Text>Število togosti</Text>
    </Item>

    <Item>
        <TextId>4004</TextId>
        <Text>Rob</Text>
    </Item>

    <Item>
        <TextId>4005</TextId>
        <Text>Vertikalna togost</Text>
    </Item>

    <Item>
        <TextId>4006</TextId>
        <Text>Center</Text>
    </Item>

    <Item>
        <TextId>4007</TextId>
        <Text>Število togosti</Text>
    </Item>

    <Item>
        <TextId>4008</TextId>
        <Text>Rob</Text>
    </Item>

    <Item>
        <TextId>4009</TextId>
        <Text>Debelina</Text>
    </Item>

    <Item>
        <TextId>4010</TextId>
        <Text>Dolžina</Text>
    </Item>

    <Item>
        <TextId>4011</TextId>
        <Text>Širina</Text>
    </Item>

    <Item>
        <TextId>4012</TextId>
        <Text>Dolžina porezovanja</Text>
    </Item>

    <Item>
        <TextId>4013</TextId>
        <Text>Layout</Text>
    </Item>

    <Item>
        <TextId>4014</TextId>
        <Text>Rob/sredina</Text>
    </Item>

    <Item>
        <TextId>4015</TextId>
        <Text>Krožna oblika</Text>
    </Item>

    <Item>
        <TextId>4016</TextId>
        <Text>Število togosti</Text>
    </Item>

    <Item>
        <TextId>4017</TextId>
        <Text>Začetni kót</Text>
    </Item>

    <!-- DIALOG LINES -->

    <Item>
        <TextId>10000</TextId>
        <Text>Izberi nosilni steber</Text>
    </Item>

    <Item>
        <TextId>10001</TextId>
        <Text>Uredi parametre</Text>
    </Item>

    <!-- POP-UP MESSAGE -->

    <Item>
        <TextId>11000</TextId>
        <Text>Nosilni steber je bil izbrisan. Ali želite izbrati drugi steber?</Text>
    </Item>

    <Item>
        <TextId>11001</TextId>
        <Text>Kopirali ste PhytonPart, ki je povezan z nosilnim stebrom. Ali ga želite povezati z novim nosilnim stebrom?</Text>
    </Item>

    <Item>
        <TextId>11002</TextId>
        <Text>Ta ukaz z vašo aktualno licenco ni združljiv</Text>
    </Item>

    <Item>
        <TextId>11003</TextId>
        <Text>Ta ukaz ni združljiv z verzijo Allplana, ki jo uporabljate.</Text>
    </Item>

    <Item>
        <TextId>11004</TextId>
        <Text>Izberite nosilni steber brez nagiba na koncu prosim.</Text>
    </Item>

    <!-- PROFILE NAME -->
    <Item>
        <TextId>12000</TextId>
        <Text>I</Text>
    </Item>

    <Item>
        <TextId>12001</TextId>
        <Text>Pravokotno votlotelo</Text>
    </Item>

    <Item>
        <TextId>12002</TextId>
        <Text>L</Text>
    </Item>

    <Item>
        <TextId>12003</TextId>
        <Text>Votel krog</Text>
    </Item>

    <Item>
        <TextId>12004</TextId>
        <Text>C</Text>
    </Item>

    <Item>
        <TextId>12005</TextId>
        <Text>T</Text>
    </Item>

    <Item>
        <TextId>12006</TextId>
        <Text>Pravokotnik</Text>
    </Item>

    <Item>
        <TextId>12007</TextId>
        <Text>Krog</Text>
    </Item>

    <Item>
        <TextId>12008</TextId>
        <Text>I asim</Text>
    </Item>

    <Item>
        <TextId>12009</TextId>
        <Text>Hladno oblikovano</Text>
    </Item>

    <Item>
        <TextId>12010</TextId>
        <Text>Z</Text>
    </Item>

    <Item>
        <TextId>12011</TextId>
        <Text>Tirnice</Text>
    </Item>

</Element>